<?xml version='1.0' encoding='UTF-8' ?>
<meta name='barista_version' content='16.0' />
<barista_admin_record>
	<barista_record_table>ADM_QUERY</barista_record_table>
	<query_id>AR_DEPOSITDET   </query_id>
	<desc>Bank Deposit Detail</desc>
	<dd_table_alias>ARE_CASHHDR     </dd_table_alias>
	<column_move>Y</column_move>
	<query_type>S</query_type>
	<default_value>N</default_value>
	<user_filters>Y</user_filters>
	<print_results>Y</print_results>
	<clip_results>Y</clip_results>
	<asc_comp_id>01007514</asc_comp_id>
	<asc_prod_id>AR </asc_prod_id>
	<override_sql>Y</override_sql>
	<sql_select>SELECT are_cashhdr.firm_id, are_cashhdr.deposit_id, are_cashhdr.receipt_date, are_cashhdr.customer_id, arm_custmast.customer_name, are_cashhdr.cash_rec_cd, arc_cashcode.code_desc, are_cashhdr.ar_check_no, are_cashhdr.payment_amt[$0a$]FROM are_cashhdr[$0a$]LEFT JOIN arm_custmast ON arm_custmast.firm_id=are_cashhdr.firm_id AND arm_custmast.customer_id=are_cashhdr.customer_id[$0a$]LEFT JOIN arc_cashcode ON arc_cashcode.firm_id=are_cashhdr.firm_id AND  arc_cashcode.cash_rec_cd=are_cashhdr.cash_rec_cd[$0a$]                                                                                                                                                                                                                                                                                                                                                                                                                                                                                                                                                                                                                                                                                                                                                                                                                                                                                                                                                                                                                                                                                                                                                                                                                                                                                                                                                                                                                                                                                                                                                                                                                                                                                                                                                                                                                                                                                                                                                                                                                                                                                                                                                                                                                                                                                                                                                                                                                                                                                                                                                                                                                                                                                                                                                                                                                                                                                                                                                                                                                                                                                                                                                                                                                                                                                                                                                                                                                                                                                                                                                                                                                                                                                                                                                                                                                                                                                                                                                                                                                                                                                                                                                                                                                                                                                                                                                                                                                                                                                                                                                                                                                                                                                                                                                                                                                                                                                                                                                                                                                                                                                                                                                                                                                                                                                                                                                                                                                                                                                                                                                                                                                                                                                                                                                                                                                                                                                                                                                                                                                                                                                                                                                                                                                                                                                                                                                                                                                                                                                                                                                                                                                                                                                                                                                                                                                                                                                                                                                                                                                                                                                                                                                                                                                                                                                                                                                                                                                                                                                                                                                                                                                                                                                                                                                                                                                                                                                                                                                                                                                         </sql_select>
	<full_search>Y</full_search>
</barista_admin_record>